urban_async-0.1.7.dist-info/METADATA
urban_async-0.1.7.dist-info/RECORD
urban_async-0.1.7.dist-info/WHEEL
urban_async-0.1.7.dist-info/top_level.txt
urbanasync/__init__.py
urbanasync/models.py
urbanasync/urban.py
