Metadata-Version: 2.1
Name: urban-async
Version: 0.1.7
Summary: An async Python API wrapper for Urban Dictionary
Home-page: https://github.com/kwugfighter/urbanasync
Author: kwugfighter
Author-email: isaacli430@gmail.com
License: MIT
Keywords: urban,async,urban py,urban dictionary
Platform: UNKNOWN
Classifier: Development Status :: 3 - Alpha
Classifier: Intended Audience :: Developers
Classifier: Topic :: Software Development :: Build Tools
Classifier: License :: OSI Approved :: MIT License
Classifier: Programming Language :: Python :: 3.5
Classifier: Programming Language :: Python :: 3.6
